o3rg-0.1.0.dist-info/METADATA
o3rg-0.1.0.dist-info/WHEEL
o3rg/__init__.py
o3rg/__init__.pyi
o3rg/o3rg.cpython-313-arm-linux-gnueabihf.so
o3rg/py.typed
o3rg-0.1.0.dist-info/RECORD
